MANIFEST.in
setup.py
chatterbox_droid_tts.egg-info/PKG-INFO
chatterbox_droid_tts.egg-info/SOURCES.txt
chatterbox_droid_tts.egg-info/dependency_links.txt
chatterbox_droid_tts.egg-info/entry_points.txt
chatterbox_droid_tts.egg-info/requires.txt
chatterbox_droid_tts.egg-info/top_level.txt
chatterbox_droid_tts.egg-info/zip-safe
chatterbox_tts_plugin_droid/__init__.py
chatterbox_tts_plugin_droid/res/droid/!_beep.wav
chatterbox_tts_plugin_droid/res/droid/+_beep.wav
chatterbox_tts_plugin_droid/res/droid/-_beep.wav
chatterbox_tts_plugin_droid/res/droid/0_beep.wav
chatterbox_tts_plugin_droid/res/droid/1_beep.wav
chatterbox_tts_plugin_droid/res/droid/2_beep.wav
chatterbox_tts_plugin_droid/res/droid/3_beep.wav
chatterbox_tts_plugin_droid/res/droid/4_beep.wav
chatterbox_tts_plugin_droid/res/droid/5_beep.wav
chatterbox_tts_plugin_droid/res/droid/6_beep.wav
chatterbox_tts_plugin_droid/res/droid/7_beep.wav
chatterbox_tts_plugin_droid/res/droid/8_beep.wav
chatterbox_tts_plugin_droid/res/droid/9_beep.wav
chatterbox_tts_plugin_droid/res/droid/A_beep.wav
chatterbox_tts_plugin_droid/res/droid/B_beep.wav
chatterbox_tts_plugin_droid/res/droid/C_beep.wav
chatterbox_tts_plugin_droid/res/droid/D_beep.wav
chatterbox_tts_plugin_droid/res/droid/E_beep.wav
chatterbox_tts_plugin_droid/res/droid/F_beep.wav
chatterbox_tts_plugin_droid/res/droid/G_beep.wav
chatterbox_tts_plugin_droid/res/droid/H_beep.wav
chatterbox_tts_plugin_droid/res/droid/I_beep.wav
chatterbox_tts_plugin_droid/res/droid/J_beep.wav
chatterbox_tts_plugin_droid/res/droid/K_beep.wav
chatterbox_tts_plugin_droid/res/droid/L_beep.wav
chatterbox_tts_plugin_droid/res/droid/M_beep.wav
chatterbox_tts_plugin_droid/res/droid/N_beep.wav
chatterbox_tts_plugin_droid/res/droid/O_beep.wav
chatterbox_tts_plugin_droid/res/droid/P_beep.wav
chatterbox_tts_plugin_droid/res/droid/Q_beep.wav
chatterbox_tts_plugin_droid/res/droid/R_beep.wav
chatterbox_tts_plugin_droid/res/droid/S_beep.wav
chatterbox_tts_plugin_droid/res/droid/T_beep.wav
chatterbox_tts_plugin_droid/res/droid/U_beep.wav
chatterbox_tts_plugin_droid/res/droid/V_beep.wav
chatterbox_tts_plugin_droid/res/droid/W_beep.wav
chatterbox_tts_plugin_droid/res/droid/X_beep.wav
chatterbox_tts_plugin_droid/res/droid/Y_beep.wav
chatterbox_tts_plugin_droid/res/droid/Z_beep.wav
